<?xml version="1.0" encoding="UTF-8"?>
<beans:beans xmlns:beans="http://www.springframework.org/schema/beans"
             xmlns:xsi="http://www.w3.org/2001/XMLSchema-instance"
             xmlns="http://www.springframework.org/schema/security"
             xsi:schemaLocation="http://www.springframework.org/schema/beans http://www.springframework.org/schema/beans/spring-beans.xsd
      http://www.springframework.org/schema/security http://www.springframework.org/schema/security/spring-security.xsd">


    <http request-matcher="regex" auto-config="true" use-expressions="true">
        <!-- web-страницы -->
        <intercept-url pattern="\/admin\/?.*" access="hasRole('ROLE_ADMIN')" method="GET"/>
        <intercept-url pattern="\/manager\/?.*" access="hasRole('ROLE_MANAGER')" method="GET"/>
        <intercept-url pattern="\/developer\/?.*" access="hasRole('ROLE_DEV')" method="GET"/>

        <!-- Rest-сервис -->
        <!-- account -->
        <intercept-url pattern="\/account\/?" access="hasAnyRole('ROLE_ADMIN', 'ROLE_MANAGER', 'ROLE_DEV')"
                       method="GET"/>
        <intercept-url pattern="\/account\/[0-9]{1,}\/?" access="hasAnyRole('ROLE_ADMIN', 'ROLE_MANAGER')"
                       method="GET"/>
        <intercept-url pattern="\/account\/?" access="hasRole('ROLE_ADMIN')" method="POST"/>
        <intercept-url pattern="\/account\/[0-9]{1,}\/?" access="hasRole('ROLE_ADMIN')" method="DELETE"/>

        <!-- project -->
        <intercept-url pattern="\/project\/?" access="hasAnyRole('ROLE_MANAGER', 'ROLE_DEV')" method="GET"/>
        <intercept-url pattern="\/project\/[0-9]{1,}\/?" access="hasRole('ROLE_MANAGER')" method="GET"/>
        <intercept-url pattern="\/project\/all_my\/?" access="hasAnyRole('ROLE_MANAGER', 'ROLE_DEV')" method="GET"/>
        <intercept-url pattern="\/project\/?" access="hasRole('ROLE_MANAGER')" method="POST"/>
        <intercept-url pattern="\/project\/[0-9]{1,}\/?" access="hasRole('ROLE_MANAGER')" method="DELETE"/>
        <intercept-url pattern="\/project\/[0-9]{1,}\/active\/?" access="hasRole('ROLE_MANAGER')" method="PUT"/>
        <intercept-url pattern="\/project\/current\/complete\/?" access="hasRole('ROLE_MANAGER')" method="PUT"/>
        <intercept-url pattern="\/project\/[0-9]{1,}\/dev\/[0-9]{1,}\/?" access="hasRole('ROLE_MANAGER')"
                       method="POST"/>
        <intercept-url pattern="\/project\/[0-9]{1,}\/dev\/[0-9]{1,}\/?" access="hasRole('ROLE_MANAGER')"
                       method="DELETE"/>
        <intercept-url pattern="\/project\/[0-9]{1,}\/dev\/all\/?" access="hasRole('ROLE_MANAGER')" method="GET"/>
        <intercept-url pattern="\/project\/dev\/avail\/?" access="hasRole('ROLE_MANAGER')" method="GET"/>
        <intercept-url pattern="\/project\/[0-9]{1,}\/comment\/all\/?" access="hasAnyRole('ROLE_MANAGER', 'ROLE_DEV')"
                       method="GET"/>
        <intercept-url pattern="\/project\/[0-9]{1,}\/comment\/?" access="hasAnyRole('ROLE_MANAGER', 'ROLE_DEV')"
                       method="POST"/>

        <csrf disabled="true"/>
        <form-login authentication-success-handler-ref="authSuccessHandler" />
    </http>

    <global-method-security jsr250-annotations="enabled" pre-post-annotations="enabled" secured-annotations="enabled"/>

    <beans:bean id="authSuccessHandler" class="com.company.service.AuthSuccessHandler" lazy-init="false"/>

    <authentication-manager alias="authenticationManager">
        <authentication-provider user-service-ref="accountService">
            <password-encoder hash="sha"/>
        </authentication-provider>
    </authentication-manager>
</beans:beans>